epydeck/__init__.py
epydeck/_version.py
epydeck-1.0.0.dist-info/LICENCE.md
epydeck-1.0.0.dist-info/METADATA
epydeck-1.0.0.dist-info/WHEEL
epydeck-1.0.0.dist-info/top_level.txt
epydeck-1.0.0.dist-info/RECORD
