Metadata-Version: 2.1
Name: epydeck
Version: 1.0.0
Summary: An EPOCH plasma PIC code input file (deck) reader/writer.
Author-email: Peter Hill <peter.hill@york.ac.uk>, Joel Adams <joel.adams@york.ac.uk>
License: GNU GENERAL PUBLIC LICENSE
Requires-Python: >=3.9
License-File: LICENCE.md
Provides-Extra: docs
Requires-Dist: sphinx>=5.3; extra == "docs"
Requires-Dist: sphinx-autodoc-typehints>=1.19; extra == "docs"
Requires-Dist: sphinx-book-theme>=0.4.0rc1; extra == "docs"
Requires-Dist: sphinx-argparse-cli>=1.10.0; extra == "docs"
Requires-Dist: sphinx-inline-tabs; extra == "docs"
Provides-Extra: tests
Requires-Dist: pytest>=3.3.0; extra == "tests"
